universal_mcp_reddit/README.md
universal_mcp_reddit/__init__.py
universal_mcp_reddit/app.py
universal_mcp_reddit/server.py
universal_mcp_reddit-0.1.10.dist-info/METADATA
universal_mcp_reddit-0.1.10.dist-info/WHEEL
universal_mcp_reddit-0.1.10.dist-info/entry_points.txt
universal_mcp_reddit-0.1.10.dist-info/licenses/LICENSE
universal_mcp_reddit-0.1.10.dist-info/RECORD
