Metadata-Version: 2.4
Name: universal-mcp-reddit
Version: 0.1.10
Summary: A Universal MCP Application: universal_mcp_reddit
Project-URL: Homepage, https://github.com/universal-mcp/reddit
Project-URL: Repository, https://github.com/universal-mcp/reddit
Author-email: Manoj Bajaj <manoj@agentr.dev>
License: MIT
License-File: LICENSE
Classifier: License :: OSI Approved :: MIT License
Classifier: Operating System :: OS Independent
Classifier: Programming Language :: Python :: 3
Classifier: Programming Language :: Python :: 3.11
Requires-Python: >=3.11
Requires-Dist: langchain-openai>=0.3.28
Requires-Dist: langgraph>=0.5.3
Requires-Dist: pytest-asyncio>=1.1.0
Requires-Dist: universal-mcp-google-mail>=0.1.11
Requires-Dist: universal-mcp==0.1.23
Provides-Extra: dev
Requires-Dist: pre-commit; extra == 'dev'
Requires-Dist: ruff; extra == 'dev'
Provides-Extra: test
Requires-Dist: pytest-cov; extra == 'test'
Requires-Dist: pytest<9.0.0,>=7.0.0; extra == 'test'
